{"nodes": [{"id": "e_all_downloads_pharmacy_erp_backend_core_guarantees_inventory_lineage_py", "label": "inventory_lineage.py", "file_type": "code", "source_file": "E:\\all downloads\\Pharmacy_ERP\\backend\\core\\guarantees\\inventory_lineage.py", "source_location": "L1"}, {"id": "guarantees_inventory_lineage_lineagenode", "label": "LineageNode", "file_type": "code", "source_file": "E:\\all downloads\\Pharmacy_ERP\\backend\\core\\guarantees\\inventory_lineage.py", "source_location": "L21"}, {"id": "guarantees_inventory_lineage_lineagevalidationresult", "label": "LineageValidationResult", "file_type": "code", "source_file": "E:\\all downloads\\Pharmacy_ERP\\backend\\core\\guarantees\\inventory_lineage.py", "source_location": "L30"}, {"id": "guarantees_inventory_lineage_inventorylineageenforcer", "label": "InventoryLineageEnforcer", "file_type": "code", "source_file": "E:\\all downloads\\Pharmacy_ERP\\backend\\core\\guarantees\\inventory_lineage.py", "source_location": "L41"}, {"id": "guarantees_inventory_lineage_inventorylineageenforcer_init", "label": ".__init__()", "file_type": "code", "source_file": "E:\\all downloads\\Pharmacy_ERP\\backend\\core\\guarantees\\inventory_lineage.py", "source_location": "L54"}, {"id": "str", "label": "str", "file_type": "code", "source_file": "E:\\all downloads\\Pharmacy_ERP\\backend\\core\\guarantees\\inventory_lineage.py", "source_location": "L54"}, {"id": "guarantees_inventory_lineage_inventorylineageenforcer_trace_batch_lineage", "label": ".trace_batch_lineage()", "file_type": "code", "source_file": "E:\\all downloads\\Pharmacy_ERP\\backend\\core\\guarantees\\inventory_lineage.py", "source_location": "L58"}, {"id": "guarantees_inventory_lineage_inventorylineageenforcer_trace_from_sale", "label": "._trace_from_sale()", "file_type": "code", "source_file": "E:\\all downloads\\Pharmacy_ERP\\backend\\core\\guarantees\\inventory_lineage.py", "source_location": "L99"}, {"id": "guarantees_inventory_lineage_inventorylineageenforcer_trace_from_return", "label": "._trace_from_return()", "file_type": "code", "source_file": "E:\\all downloads\\Pharmacy_ERP\\backend\\core\\guarantees\\inventory_lineage.py", "source_location": "L114"}, {"id": "guarantees_inventory_lineage_inventorylineageenforcer_trace_from_purchase", "label": "._trace_from_purchase()", "file_type": "code", "source_file": "E:\\all downloads\\Pharmacy_ERP\\backend\\core\\guarantees\\inventory_lineage.py", "source_location": "L139"}, {"id": "guarantees_inventory_lineage_inventorylineageenforcer_trace_from_transfer", "label": "._trace_from_transfer()", "file_type": "code", "source_file": "E:\\all downloads\\Pharmacy_ERP\\backend\\core\\guarantees\\inventory_lineage.py", "source_location": "L154"}, {"id": "guarantees_inventory_lineage_inventorylineageenforcer_validate_batch_lineage", "label": ".validate_batch_lineage()", "file_type": "code", "source_file": "E:\\all downloads\\Pharmacy_ERP\\backend\\core\\guarantees\\inventory_lineage.py", "source_location": "L161"}, {"id": "decimal", "label": "Decimal", "file_type": "code", "source_file": "E:\\all downloads\\Pharmacy_ERP\\backend\\core\\guarantees\\inventory_lineage.py", "source_location": "L161"}, {"id": "guarantees_inventory_lineage_inventorylineageenforcer_validate_all_batches", "label": ".validate_all_batches()", "file_type": "code", "source_file": "E:\\all downloads\\Pharmacy_ERP\\backend\\core\\guarantees\\inventory_lineage.py", "source_location": "L202"}, {"id": "guarantees_inventory_lineage_inventorylineageenforcer_check_batch_consistency", "label": ".check_batch_consistency()", "file_type": "code", "source_file": "E:\\all downloads\\Pharmacy_ERP\\backend\\core\\guarantees\\inventory_lineage.py", "source_location": "L210"}, {"id": "guarantees_inventory_lineage_inventorylineageenforcer_has_violations", "label": ".has_violations()", "file_type": "code", "source_file": "E:\\all downloads\\Pharmacy_ERP\\backend\\core\\guarantees\\inventory_lineage.py", "source_location": "L233"}, {"id": "bool", "label": "bool", "file_type": "code", "source_file": "E:\\all downloads\\Pharmacy_ERP\\backend\\core\\guarantees\\inventory_lineage.py", "source_location": "L233"}, {"id": "guarantees_inventory_lineage_inventorylineageenforcer_violation_count", "label": ".violation_count()", "file_type": "code", "source_file": "E:\\all downloads\\Pharmacy_ERP\\backend\\core\\guarantees\\inventory_lineage.py", "source_location": "L237"}, {"id": "int", "label": "int", "file_type": "code", "source_file": "E:\\all downloads\\Pharmacy_ERP\\backend\\core\\guarantees\\inventory_lineage.py", "source_location": "L237"}, {"id": "guarantees_inventory_lineage_inventorylineageenforcer_clear", "label": ".clear()", "file_type": "code", "source_file": "E:\\all downloads\\Pharmacy_ERP\\backend\\core\\guarantees\\inventory_lineage.py", "source_location": "L240"}, {"id": "guarantees_inventory_lineage_get_lineage_enforcer", "label": "get_lineage_enforcer()", "file_type": "code", "source_file": "E:\\all downloads\\Pharmacy_ERP\\backend\\core\\guarantees\\inventory_lineage.py", "source_location": "L247"}, {"id": "guarantees_inventory_lineage_rationale_1", "label": "Class 5: InventoryLineageEnforcer \u2014 Inventory Lineage Guarantee.  GUARANTEE: Inv", "file_type": "rationale", "source_file": "E:\\all downloads\\Pharmacy_ERP\\backend\\core\\guarantees\\inventory_lineage.py", "source_location": "L1"}, {"id": "guarantees_inventory_lineage_rationale_42", "label": "Enforces that all inventory changes are traceable through the     lineage graph", "file_type": "rationale", "source_file": "E:\\all downloads\\Pharmacy_ERP\\backend\\core\\guarantees\\inventory_lineage.py", "source_location": "L42"}, {"id": "guarantees_inventory_lineage_rationale_59", "label": "Trace the full lineage of a batch from inception through all movements.", "file_type": "rationale", "source_file": "E:\\all downloads\\Pharmacy_ERP\\backend\\core\\guarantees\\inventory_lineage.py", "source_location": "L59"}, {"id": "guarantees_inventory_lineage_rationale_162", "label": "Validate that a batch's current quantity matches the lineage-derived quantity.", "file_type": "rationale", "source_file": "E:\\all downloads\\Pharmacy_ERP\\backend\\core\\guarantees\\inventory_lineage.py", "source_location": "L162"}, {"id": "guarantees_inventory_lineage_rationale_203", "label": "Validate lineage for every batch in the system.", "file_type": "rationale", "source_file": "E:\\all downloads\\Pharmacy_ERP\\backend\\core\\guarantees\\inventory_lineage.py", "source_location": "L203"}, {"id": "guarantees_inventory_lineage_rationale_211", "label": "Verify that a batch's product and warehouse match the invoice item's context.", "file_type": "rationale", "source_file": "E:\\all downloads\\Pharmacy_ERP\\backend\\core\\guarantees\\inventory_lineage.py", "source_location": "L211"}], "edges": [{"source": "e_all_downloads_pharmacy_erp_backend_core_guarantees_inventory_lineage_py", "target": "dataclasses", "relation": "imports_from", "context": "import", "confidence": "EXTRACTED", "source_file": "E:\\all downloads\\Pharmacy_ERP\\backend\\core\\guarantees\\inventory_lineage.py", "source_location": "L14", "weight": 1.0}, {"source": "e_all_downloads_pharmacy_erp_backend_core_guarantees_inventory_lineage_py", "target": "decimal", "relation": "imports_from", "context": "import", "confidence": "EXTRACTED", "source_file": "E:\\all downloads\\Pharmacy_ERP\\backend\\core\\guarantees\\inventory_lineage.py", "source_location": "L15", "weight": 1.0}, {"source": "e_all_downloads_pharmacy_erp_backend_core_guarantees_inventory_lineage_py", "target": "typing", "relation": "imports_from", "context": "import", "confidence": "EXTRACTED", "source_file": "E:\\all downloads\\Pharmacy_ERP\\backend\\core\\guarantees\\inventory_lineage.py", "source_location": "L16", "weight": 1.0}, {"source": "e_all_downloads_pharmacy_erp_backend_core_guarantees_inventory_lineage_py", "target": "django_db", "relation": "imports_from", "context": "import", "confidence": "EXTRACTED", "source_file": "E:\\all downloads\\Pharmacy_ERP\\backend\\core\\guarantees\\inventory_lineage.py", "source_location": "L17", "weight": 1.0}, {"source": "e_all_downloads_pharmacy_erp_backend_core_guarantees_inventory_lineage_py", "target": "guarantees_inventory_lineage_lineagenode", "relation": "contains", "confidence": "EXTRACTED", "source_file": "E:\\all downloads\\Pharmacy_ERP\\backend\\core\\guarantees\\inventory_lineage.py", "source_location": "L21", "weight": 1.0}, {"source": "e_all_downloads_pharmacy_erp_backend_core_guarantees_inventory_lineage_py", "target": "guarantees_inventory_lineage_lineagevalidationresult", "relation": "contains", "confidence": "EXTRACTED", "source_file": "E:\\all downloads\\Pharmacy_ERP\\backend\\core\\guarantees\\inventory_lineage.py", "source_location": "L30", "weight": 1.0}, {"source": "e_all_downloads_pharmacy_erp_backend_core_guarantees_inventory_lineage_py", "target": "guarantees_inventory_lineage_inventorylineageenforcer", "relation": "contains", "confidence": "EXTRACTED", "source_file": "E:\\all downloads\\Pharmacy_ERP\\backend\\core\\guarantees\\inventory_lineage.py", "source_location": "L41", "weight": 1.0}, {"source": "guarantees_inventory_lineage_inventorylineageenforcer", "target": "guarantees_inventory_lineage_inventorylineageenforcer_init", "relation": "method", "confidence": "EXTRACTED", "source_file": "E:\\all downloads\\Pharmacy_ERP\\backend\\core\\guarantees\\inventory_lineage.py", "source_location": "L54", "weight": 1.0}, {"source": "guarantees_inventory_lineage_inventorylineageenforcer_init", "target": "str", "relation": "references", "context": "parameter_type", "confidence": "EXTRACTED", "source_file": "E:\\all downloads\\Pharmacy_ERP\\backend\\core\\guarantees\\inventory_lineage.py", "source_location": "L54", "weight": 1.0}, {"source": "guarantees_inventory_lineage_inventorylineageenforcer", "target": "guarantees_inventory_lineage_inventorylineageenforcer_trace_batch_lineage", "relation": "method", "confidence": "EXTRACTED", "source_file": "E:\\all downloads\\Pharmacy_ERP\\backend\\core\\guarantees\\inventory_lineage.py", "source_location": "L58", "weight": 1.0}, {"source": "guarantees_inventory_lineage_inventorylineageenforcer_trace_batch_lineage", "target": "guarantees_inventory_lineage_lineagenode", "relation": "references", "context": "return_type", "confidence": "EXTRACTED", "source_file": "E:\\all downloads\\Pharmacy_ERP\\backend\\core\\guarantees\\inventory_lineage.py", "source_location": "L58", "weight": 1.0}, {"source": "guarantees_inventory_lineage_inventorylineageenforcer", "target": "guarantees_inventory_lineage_inventorylineageenforcer_trace_from_sale", "relation": "method", "confidence": "EXTRACTED", "source_file": "E:\\all downloads\\Pharmacy_ERP\\backend\\core\\guarantees\\inventory_lineage.py", "source_location": "L99", "weight": 1.0}, {"source": "guarantees_inventory_lineage_inventorylineageenforcer_trace_from_sale", "target": "str", "relation": "references", "context": "parameter_type", "confidence": "EXTRACTED", "source_file": "E:\\all downloads\\Pharmacy_ERP\\backend\\core\\guarantees\\inventory_lineage.py", "source_location": "L99", "weight": 1.0}, {"source": "guarantees_inventory_lineage_inventorylineageenforcer_trace_from_sale", "target": "guarantees_inventory_lineage_lineagenode", "relation": "references", "context": "generic_arg", "confidence": "EXTRACTED", "source_file": "E:\\all downloads\\Pharmacy_ERP\\backend\\core\\guarantees\\inventory_lineage.py", "source_location": "L99", "weight": 1.0}, {"source": "guarantees_inventory_lineage_inventorylineageenforcer", "target": "guarantees_inventory_lineage_inventorylineageenforcer_trace_from_return", "relation": "method", "confidence": "EXTRACTED", "source_file": "E:\\all downloads\\Pharmacy_ERP\\backend\\core\\guarantees\\inventory_lineage.py", "source_location": "L114", "weight": 1.0}, {"source": "guarantees_inventory_lineage_inventorylineageenforcer_trace_from_return", "target": "str", "relation": "references", "context": "parameter_type", "confidence": "EXTRACTED", "source_file": "E:\\all downloads\\Pharmacy_ERP\\backend\\core\\guarantees\\inventory_lineage.py", "source_location": "L114", "weight": 1.0}, {"source": "guarantees_inventory_lineage_inventorylineageenforcer_trace_from_return", "target": "guarantees_inventory_lineage_lineagenode", "relation": "references", "context": "generic_arg", "confidence": "EXTRACTED", "source_file": "E:\\all downloads\\Pharmacy_ERP\\backend\\core\\guarantees\\inventory_lineage.py", "source_location": "L114", "weight": 1.0}, {"source": "guarantees_inventory_lineage_inventorylineageenforcer", "target": "guarantees_inventory_lineage_inventorylineageenforcer_trace_from_purchase", "relation": "method", "confidence": "EXTRACTED", "source_file": "E:\\all downloads\\Pharmacy_ERP\\backend\\core\\guarantees\\inventory_lineage.py", "source_location": "L139", "weight": 1.0}, {"source": "guarantees_inventory_lineage_inventorylineageenforcer_trace_from_purchase", "target": "str", "relation": "references", "context": "parameter_type", "confidence": "EXTRACTED", "source_file": "E:\\all downloads\\Pharmacy_ERP\\backend\\core\\guarantees\\inventory_lineage.py", "source_location": "L139", "weight": 1.0}, {"source": "guarantees_inventory_lineage_inventorylineageenforcer_trace_from_purchase", "target": "guarantees_inventory_lineage_lineagenode", "relation": "references", "context": "generic_arg", "confidence": "EXTRACTED", "source_file": "E:\\all downloads\\Pharmacy_ERP\\backend\\core\\guarantees\\inventory_lineage.py", "source_location": "L139", "weight": 1.0}, {"source": "guarantees_inventory_lineage_inventorylineageenforcer", "target": "guarantees_inventory_lineage_inventorylineageenforcer_trace_from_transfer", "relation": "method", "confidence": "EXTRACTED", "source_file": "E:\\all downloads\\Pharmacy_ERP\\backend\\core\\guarantees\\inventory_lineage.py", "source_location": "L154", "weight": 1.0}, {"source": "guarantees_inventory_lineage_inventorylineageenforcer_trace_from_transfer", "target": "str", "relation": "references", "context": "parameter_type", "confidence": "EXTRACTED", "source_file": "E:\\all downloads\\Pharmacy_ERP\\backend\\core\\guarantees\\inventory_lineage.py", "source_location": "L154", "weight": 1.0}, {"source": "guarantees_inventory_lineage_inventorylineageenforcer_trace_from_transfer", "target": "guarantees_inventory_lineage_lineagenode", "relation": "references", "context": "generic_arg", "confidence": "EXTRACTED", "source_file": "E:\\all downloads\\Pharmacy_ERP\\backend\\core\\guarantees\\inventory_lineage.py", "source_location": "L154", "weight": 1.0}, {"source": "guarantees_inventory_lineage_inventorylineageenforcer", "target": "guarantees_inventory_lineage_inventorylineageenforcer_validate_batch_lineage", "relation": "method", "confidence": "EXTRACTED", "source_file": "E:\\all downloads\\Pharmacy_ERP\\backend\\core\\guarantees\\inventory_lineage.py", "source_location": "L161", "weight": 1.0}, {"source": "guarantees_inventory_lineage_inventorylineageenforcer_validate_batch_lineage", "target": "decimal", "relation": "references", "context": "generic_arg", "confidence": "EXTRACTED", "source_file": "E:\\all downloads\\Pharmacy_ERP\\backend\\core\\guarantees\\inventory_lineage.py", "source_location": "L161", "weight": 1.0}, {"source": "guarantees_inventory_lineage_inventorylineageenforcer_validate_batch_lineage", "target": "guarantees_inventory_lineage_lineagevalidationresult", "relation": "references", "context": "return_type", "confidence": "EXTRACTED", "source_file": "E:\\all downloads\\Pharmacy_ERP\\backend\\core\\guarantees\\inventory_lineage.py", "source_location": "L161", "weight": 1.0}, {"source": "guarantees_inventory_lineage_inventorylineageenforcer", "target": "guarantees_inventory_lineage_inventorylineageenforcer_validate_all_batches", "relation": "method", "confidence": "EXTRACTED", "source_file": "E:\\all downloads\\Pharmacy_ERP\\backend\\core\\guarantees\\inventory_lineage.py", "source_location": "L202", "weight": 1.0}, {"source": "guarantees_inventory_lineage_inventorylineageenforcer_validate_all_batches", "target": "str", "relation": "references", "context": "generic_arg", "confidence": "EXTRACTED", "source_file": "E:\\all downloads\\Pharmacy_ERP\\backend\\core\\guarantees\\inventory_lineage.py", "source_location": "L202", "weight": 1.0}, {"source": "guarantees_inventory_lineage_inventorylineageenforcer_validate_all_batches", "target": "guarantees_inventory_lineage_lineagevalidationresult", "relation": "references", "context": "generic_arg", "confidence": "EXTRACTED", "source_file": "E:\\all downloads\\Pharmacy_ERP\\backend\\core\\guarantees\\inventory_lineage.py", "source_location": "L202", "weight": 1.0}, {"source": "guarantees_inventory_lineage_inventorylineageenforcer", "target": "guarantees_inventory_lineage_inventorylineageenforcer_check_batch_consistency", "relation": "method", "confidence": "EXTRACTED", "source_file": "E:\\all downloads\\Pharmacy_ERP\\backend\\core\\guarantees\\inventory_lineage.py", "source_location": "L210", "weight": 1.0}, {"source": "guarantees_inventory_lineage_inventorylineageenforcer", "target": "guarantees_inventory_lineage_inventorylineageenforcer_has_violations", "relation": "method", "confidence": "EXTRACTED", "source_file": "E:\\all downloads\\Pharmacy_ERP\\backend\\core\\guarantees\\inventory_lineage.py", "source_location": "L233", "weight": 1.0}, {"source": "guarantees_inventory_lineage_inventorylineageenforcer_has_violations", "target": "bool", "relation": "references", "context": "return_type", "confidence": "EXTRACTED", "source_file": "E:\\all downloads\\Pharmacy_ERP\\backend\\core\\guarantees\\inventory_lineage.py", "source_location": "L233", "weight": 1.0}, {"source": "guarantees_inventory_lineage_inventorylineageenforcer", "target": "guarantees_inventory_lineage_inventorylineageenforcer_violation_count", "relation": "method", "confidence": "EXTRACTED", "source_file": "E:\\all downloads\\Pharmacy_ERP\\backend\\core\\guarantees\\inventory_lineage.py", "source_location": "L237", "weight": 1.0}, {"source": "guarantees_inventory_lineage_inventorylineageenforcer_violation_count", "target": "int", "relation": "references", "context": "return_type", "confidence": "EXTRACTED", "source_file": "E:\\all downloads\\Pharmacy_ERP\\backend\\core\\guarantees\\inventory_lineage.py", "source_location": "L237", "weight": 1.0}, {"source": "guarantees_inventory_lineage_inventorylineageenforcer", "target": "guarantees_inventory_lineage_inventorylineageenforcer_clear", "relation": "method", "confidence": "EXTRACTED", "source_file": "E:\\all downloads\\Pharmacy_ERP\\backend\\core\\guarantees\\inventory_lineage.py", "source_location": "L240", "weight": 1.0}, {"source": "e_all_downloads_pharmacy_erp_backend_core_guarantees_inventory_lineage_py", "target": "guarantees_inventory_lineage_get_lineage_enforcer", "relation": "contains", "confidence": "EXTRACTED", "source_file": "E:\\all downloads\\Pharmacy_ERP\\backend\\core\\guarantees\\inventory_lineage.py", "source_location": "L247", "weight": 1.0}, {"source": "guarantees_inventory_lineage_get_lineage_enforcer", "target": "str", "relation": "references", "context": "parameter_type", "confidence": "EXTRACTED", "source_file": "E:\\all downloads\\Pharmacy_ERP\\backend\\core\\guarantees\\inventory_lineage.py", "source_location": "L247", "weight": 1.0}, {"source": "guarantees_inventory_lineage_get_lineage_enforcer", "target": "guarantees_inventory_lineage_inventorylineageenforcer", "relation": "references", "context": "return_type", "confidence": "EXTRACTED", "source_file": "E:\\all downloads\\Pharmacy_ERP\\backend\\core\\guarantees\\inventory_lineage.py", "source_location": "L247", "weight": 1.0}, {"source": "guarantees_inventory_lineage_inventorylineageenforcer_trace_batch_lineage", "target": "guarantees_inventory_lineage_lineagenode", "relation": "calls", "context": "call", "confidence": "EXTRACTED", "source_file": "E:\\all downloads\\Pharmacy_ERP\\backend\\core\\guarantees\\inventory_lineage.py", "source_location": "L63", "weight": 1.0}, {"source": "guarantees_inventory_lineage_inventorylineageenforcer_trace_batch_lineage", "target": "decimal", "relation": "calls", "context": "call", "confidence": "EXTRACTED", "source_file": "E:\\all downloads\\Pharmacy_ERP\\backend\\core\\guarantees\\inventory_lineage.py", "source_location": "L67", "weight": 1.0}, {"source": "guarantees_inventory_lineage_inventorylineageenforcer_trace_batch_lineage", "target": "guarantees_inventory_lineage_inventorylineageenforcer_trace_from_sale", "relation": "calls", "context": "call", "confidence": "EXTRACTED", "source_file": "E:\\all downloads\\Pharmacy_ERP\\backend\\core\\guarantees\\inventory_lineage.py", "source_location": "L87", "weight": 1.0}, {"source": "guarantees_inventory_lineage_inventorylineageenforcer_trace_batch_lineage", "target": "guarantees_inventory_lineage_inventorylineageenforcer_trace_from_return", "relation": "calls", "context": "call", "confidence": "EXTRACTED", "source_file": "E:\\all downloads\\Pharmacy_ERP\\backend\\core\\guarantees\\inventory_lineage.py", "source_location": "L89", "weight": 1.0}, {"source": "guarantees_inventory_lineage_inventorylineageenforcer_trace_batch_lineage", "target": "guarantees_inventory_lineage_inventorylineageenforcer_trace_from_purchase", "relation": "calls", "context": "call", "confidence": "EXTRACTED", "source_file": "E:\\all downloads\\Pharmacy_ERP\\backend\\core\\guarantees\\inventory_lineage.py", "source_location": "L91", "weight": 1.0}, {"source": "guarantees_inventory_lineage_inventorylineageenforcer_trace_batch_lineage", "target": "guarantees_inventory_lineage_inventorylineageenforcer_trace_from_transfer", "relation": "calls", "context": "call", "confidence": "EXTRACTED", "source_file": "E:\\all downloads\\Pharmacy_ERP\\backend\\core\\guarantees\\inventory_lineage.py", "source_location": "L93", "weight": 1.0}, {"source": "guarantees_inventory_lineage_inventorylineageenforcer_trace_from_sale", "target": "guarantees_inventory_lineage_lineagenode", "relation": "calls", "context": "call", "confidence": "EXTRACTED", "source_file": "E:\\all downloads\\Pharmacy_ERP\\backend\\core\\guarantees\\inventory_lineage.py", "source_location": "L104", "weight": 1.0}, {"source": "guarantees_inventory_lineage_inventorylineageenforcer_trace_from_sale", "target": "decimal", "relation": "calls", "context": "call", "confidence": "EXTRACTED", "source_file": "E:\\all downloads\\Pharmacy_ERP\\backend\\core\\guarantees\\inventory_lineage.py", "source_location": "L108", "weight": 1.0}, {"source": "guarantees_inventory_lineage_inventorylineageenforcer_trace_from_return", "target": "guarantees_inventory_lineage_lineagenode", "relation": "calls", "context": "call", "confidence": "EXTRACTED", "source_file": "E:\\all downloads\\Pharmacy_ERP\\backend\\core\\guarantees\\inventory_lineage.py", "source_location": "L122", "weight": 1.0}, {"source": "guarantees_inventory_lineage_inventorylineageenforcer_trace_from_return", "target": "decimal", "relation": "calls", "context": "call", "confidence": "EXTRACTED", "source_file": "E:\\all downloads\\Pharmacy_ERP\\backend\\core\\guarantees\\inventory_lineage.py", "source_location": "L126", "weight": 1.0}, {"source": "guarantees_inventory_lineage_inventorylineageenforcer_trace_from_purchase", "target": "guarantees_inventory_lineage_lineagenode", "relation": "calls", "context": "call", "confidence": "EXTRACTED", "source_file": "E:\\all downloads\\Pharmacy_ERP\\backend\\core\\guarantees\\inventory_lineage.py", "source_location": "L144", "weight": 1.0}, {"source": "guarantees_inventory_lineage_inventorylineageenforcer_trace_from_purchase", "target": "decimal", "relation": "calls", "context": "call", "confidence": "EXTRACTED", "source_file": "E:\\all downloads\\Pharmacy_ERP\\backend\\core\\guarantees\\inventory_lineage.py", "source_location": "L148", "weight": 1.0}, {"source": "guarantees_inventory_lineage_inventorylineageenforcer_trace_from_transfer", "target": "guarantees_inventory_lineage_lineagenode", "relation": "calls", "context": "call", "confidence": "EXTRACTED", "source_file": "E:\\all downloads\\Pharmacy_ERP\\backend\\core\\guarantees\\inventory_lineage.py", "source_location": "L155", "weight": 1.0}, {"source": "guarantees_inventory_lineage_inventorylineageenforcer_validate_batch_lineage", "target": "decimal", "relation": "calls", "context": "call", "confidence": "EXTRACTED", "source_file": "E:\\all downloads\\Pharmacy_ERP\\backend\\core\\guarantees\\inventory_lineage.py", "source_location": "L168", "weight": 1.0}, {"source": "guarantees_inventory_lineage_inventorylineageenforcer_validate_batch_lineage", "target": "guarantees_inventory_lineage_lineagevalidationresult", "relation": "calls", "context": "call", "confidence": "EXTRACTED", "source_file": "E:\\all downloads\\Pharmacy_ERP\\backend\\core\\guarantees\\inventory_lineage.py", "source_location": "L191", "weight": 1.0}, {"source": "guarantees_inventory_lineage_inventorylineageenforcer_validate_all_batches", "target": "guarantees_inventory_lineage_inventorylineageenforcer_validate_batch_lineage", "relation": "calls", "context": "call", "confidence": "EXTRACTED", "source_file": "E:\\all downloads\\Pharmacy_ERP\\backend\\core\\guarantees\\inventory_lineage.py", "source_location": "L207", "weight": 1.0}, {"source": "guarantees_inventory_lineage_get_lineage_enforcer", "target": "guarantees_inventory_lineage_inventorylineageenforcer", "relation": "calls", "context": "call", "confidence": "EXTRACTED", "source_file": "E:\\all downloads\\Pharmacy_ERP\\backend\\core\\guarantees\\inventory_lineage.py", "source_location": "L250", "weight": 1.0}, {"source": "guarantees_inventory_lineage_rationale_1", "target": "e_all_downloads_pharmacy_erp_backend_core_guarantees_inventory_lineage_py", "relation": "rationale_for", "confidence": "EXTRACTED", "source_file": "E:\\all downloads\\Pharmacy_ERP\\backend\\core\\guarantees\\inventory_lineage.py", "source_location": "L1", "weight": 1.0}, {"source": "guarantees_inventory_lineage_rationale_42", "target": "guarantees_inventory_lineage_inventorylineageenforcer", "relation": "rationale_for", "confidence": "EXTRACTED", "source_file": "E:\\all downloads\\Pharmacy_ERP\\backend\\core\\guarantees\\inventory_lineage.py", "source_location": "L42", "weight": 1.0}, {"source": "guarantees_inventory_lineage_rationale_59", "target": "guarantees_inventory_lineage_inventorylineageenforcer_trace_batch_lineage", "relation": "rationale_for", "confidence": "EXTRACTED", "source_file": "E:\\all downloads\\Pharmacy_ERP\\backend\\core\\guarantees\\inventory_lineage.py", "source_location": "L59", "weight": 1.0}, {"source": "guarantees_inventory_lineage_rationale_162", "target": "guarantees_inventory_lineage_inventorylineageenforcer_validate_batch_lineage", "relation": "rationale_for", "confidence": "EXTRACTED", "source_file": "E:\\all downloads\\Pharmacy_ERP\\backend\\core\\guarantees\\inventory_lineage.py", "source_location": "L162", "weight": 1.0}, {"source": "guarantees_inventory_lineage_rationale_203", "target": "guarantees_inventory_lineage_inventorylineageenforcer_validate_all_batches", "relation": "rationale_for", "confidence": "EXTRACTED", "source_file": "E:\\all downloads\\Pharmacy_ERP\\backend\\core\\guarantees\\inventory_lineage.py", "source_location": "L203", "weight": 1.0}, {"source": "guarantees_inventory_lineage_rationale_211", "target": "guarantees_inventory_lineage_inventorylineageenforcer_check_batch_consistency", "relation": "rationale_for", "confidence": "EXTRACTED", "source_file": "E:\\all downloads\\Pharmacy_ERP\\backend\\core\\guarantees\\inventory_lineage.py", "source_location": "L211", "weight": 1.0}], "raw_calls": [{"caller_nid": "guarantees_inventory_lineage_inventorylineageenforcer_trace_batch_lineage", "callee": "order_by", "is_member_call": true, "source_file": "E:\\all downloads\\Pharmacy_ERP\\backend\\core\\guarantees\\inventory_lineage.py", "source_location": "L71"}, {"caller_nid": "guarantees_inventory_lineage_inventorylineageenforcer_trace_batch_lineage", "callee": "append", "is_member_call": true, "source_file": "E:\\all downloads\\Pharmacy_ERP\\backend\\core\\guarantees\\inventory_lineage.py", "source_location": "L95"}, {"caller_nid": "guarantees_inventory_lineage_inventorylineageenforcer_trace_from_sale", "callee": "first", "is_member_call": true, "source_file": "E:\\all downloads\\Pharmacy_ERP\\backend\\core\\guarantees\\inventory_lineage.py", "source_location": "L102"}, {"caller_nid": "guarantees_inventory_lineage_inventorylineageenforcer_trace_from_return", "callee": "first", "is_member_call": true, "source_file": "E:\\all downloads\\Pharmacy_ERP\\backend\\core\\guarantees\\inventory_lineage.py", "source_location": "L117"}, {"caller_nid": "guarantees_inventory_lineage_inventorylineageenforcer_trace_from_purchase", "callee": "first", "is_member_call": true, "source_file": "E:\\all downloads\\Pharmacy_ERP\\backend\\core\\guarantees\\inventory_lineage.py", "source_location": "L142"}, {"caller_nid": "guarantees_inventory_lineage_inventorylineageenforcer_validate_batch_lineage", "callee": "append", "is_member_call": true, "source_file": "E:\\all downloads\\Pharmacy_ERP\\backend\\core\\guarantees\\inventory_lineage.py", "source_location": "L176"}, {"caller_nid": "guarantees_inventory_lineage_inventorylineageenforcer_validate_batch_lineage", "callee": "append", "is_member_call": true, "source_file": "E:\\all downloads\\Pharmacy_ERP\\backend\\core\\guarantees\\inventory_lineage.py", "source_location": "L186"}, {"caller_nid": "guarantees_inventory_lineage_inventorylineageenforcer_validate_batch_lineage", "callee": "append", "is_member_call": true, "source_file": "E:\\all downloads\\Pharmacy_ERP\\backend\\core\\guarantees\\inventory_lineage.py", "source_location": "L187"}, {"caller_nid": "guarantees_inventory_lineage_inventorylineageenforcer_validate_batch_lineage", "callee": "AssertionError", "is_member_call": false, "source_file": "E:\\all downloads\\Pharmacy_ERP\\backend\\core\\guarantees\\inventory_lineage.py", "source_location": "L189"}, {"caller_nid": "guarantees_inventory_lineage_inventorylineageenforcer_validate_batch_lineage", "callee": "count", "is_member_call": true, "source_file": "E:\\all downloads\\Pharmacy_ERP\\backend\\core\\guarantees\\inventory_lineage.py", "source_location": "L198"}, {"caller_nid": "guarantees_inventory_lineage_inventorylineageenforcer_validate_all_batches", "callee": "iterator", "is_member_call": true, "source_file": "E:\\all downloads\\Pharmacy_ERP\\backend\\core\\guarantees\\inventory_lineage.py", "source_location": "L206"}, {"caller_nid": "guarantees_inventory_lineage_inventorylineageenforcer_check_batch_consistency", "callee": "append", "is_member_call": true, "source_file": "E:\\all downloads\\Pharmacy_ERP\\backend\\core\\guarantees\\inventory_lineage.py", "source_location": "L218"}, {"caller_nid": "guarantees_inventory_lineage_inventorylineageenforcer_check_batch_consistency", "callee": "append", "is_member_call": true, "source_file": "E:\\all downloads\\Pharmacy_ERP\\backend\\core\\guarantees\\inventory_lineage.py", "source_location": "L222"}, {"caller_nid": "guarantees_inventory_lineage_inventorylineageenforcer_check_batch_consistency", "callee": "join", "is_member_call": true, "source_file": "E:\\all downloads\\Pharmacy_ERP\\backend\\core\\guarantees\\inventory_lineage.py", "source_location": "L226"}, {"caller_nid": "guarantees_inventory_lineage_inventorylineageenforcer_check_batch_consistency", "callee": "append", "is_member_call": true, "source_file": "E:\\all downloads\\Pharmacy_ERP\\backend\\core\\guarantees\\inventory_lineage.py", "source_location": "L228"}, {"caller_nid": "guarantees_inventory_lineage_inventorylineageenforcer_check_batch_consistency", "callee": "AssertionError", "is_member_call": false, "source_file": "E:\\all downloads\\Pharmacy_ERP\\backend\\core\\guarantees\\inventory_lineage.py", "source_location": "L230"}]}