{"nodes": [{"id": "e_all_downloads_pharmacy_erp_frontend_enterprise_certification_certifier_py", "label": "certifier.py", "file_type": "code", "source_file": "E:\\all downloads\\Pharmacy_ERP\\frontend\\enterprise_certification\\certifier.py", "source_location": "L1"}, {"id": "enterprise_certification_certifier_enterpriseuxcertifier", "label": "EnterpriseUxCertifier", "file_type": "code", "source_file": "E:\\all downloads\\Pharmacy_ERP\\frontend\\enterprise_certification\\certifier.py", "source_location": "L22"}, {"id": "enterprise_certification_certifier_enterpriseuxcertifier_init", "label": ".__init__()", "file_type": "code", "source_file": "E:\\all downloads\\Pharmacy_ERP\\frontend\\enterprise_certification\\certifier.py", "source_location": "L30"}, {"id": "enterprise_certification_certifier_enterpriseuxcertifier_file_exists", "label": "._file_exists()", "file_type": "code", "source_file": "E:\\all downloads\\Pharmacy_ERP\\frontend\\enterprise_certification\\certifier.py", "source_location": "L45"}, {"id": "str", "label": "str", "file_type": "code", "source_file": "E:\\all downloads\\Pharmacy_ERP\\frontend\\enterprise_certification\\certifier.py", "source_location": "L45"}, {"id": "bool", "label": "bool", "file_type": "code", "source_file": "E:\\all downloads\\Pharmacy_ERP\\frontend\\enterprise_certification\\certifier.py", "source_location": "L45"}, {"id": "enterprise_certification_certifier_enterpriseuxcertifier_read_file", "label": "._read_file()", "file_type": "code", "source_file": "E:\\all downloads\\Pharmacy_ERP\\frontend\\enterprise_certification\\certifier.py", "source_location": "L48"}, {"id": "enterprise_certification_certifier_enterpriseuxcertifier_has_class", "label": "._has_class()", "file_type": "code", "source_file": "E:\\all downloads\\Pharmacy_ERP\\frontend\\enterprise_certification\\certifier.py", "source_location": "L55"}, {"id": "enterprise_certification_certifier_enterpriseuxcertifier_has_method", "label": "._has_method()", "file_type": "code", "source_file": "E:\\all downloads\\Pharmacy_ERP\\frontend\\enterprise_certification\\certifier.py", "source_location": "L58"}, {"id": "enterprise_certification_certifier_enterpriseuxcertifier_has_import", "label": "._has_import()", "file_type": "code", "source_file": "E:\\all downloads\\Pharmacy_ERP\\frontend\\enterprise_certification\\certifier.py", "source_location": "L61"}, {"id": "enterprise_certification_certifier_enterpriseuxcertifier_count_pattern", "label": "._count_pattern()", "file_type": "code", "source_file": "E:\\all downloads\\Pharmacy_ERP\\frontend\\enterprise_certification\\certifier.py", "source_location": "L64"}, {"id": "int", "label": "int", "file_type": "code", "source_file": "E:\\all downloads\\Pharmacy_ERP\\frontend\\enterprise_certification\\certifier.py", "source_location": "L64"}, {"id": "enterprise_certification_certifier_enterpriseuxcertifier_score_boolean", "label": "._score_boolean()", "file_type": "code", "source_file": "E:\\all downloads\\Pharmacy_ERP\\frontend\\enterprise_certification\\certifier.py", "source_location": "L67"}, {"id": "enterprise_certification_certifier_enterpriseuxcertifier_certify_form_system", "label": "._certify_form_system()", "file_type": "code", "source_file": "E:\\all downloads\\Pharmacy_ERP\\frontend\\enterprise_certification\\certifier.py", "source_location": "L72"}, {"id": "any", "label": "Any", "file_type": "code", "source_file": "E:\\all downloads\\Pharmacy_ERP\\frontend\\enterprise_certification\\certifier.py", "source_location": "L72"}, {"id": "enterprise_certification_certifier_enterpriseuxcertifier_certify_table_system", "label": "._certify_table_system()", "file_type": "code", "source_file": "E:\\all downloads\\Pharmacy_ERP\\frontend\\enterprise_certification\\certifier.py", "source_location": "L102"}, {"id": "enterprise_certification_certifier_enterpriseuxcertifier_certify_operator_safety", "label": "._certify_operator_safety()", "file_type": "code", "source_file": "E:\\all downloads\\Pharmacy_ERP\\frontend\\enterprise_certification\\certifier.py", "source_location": "L133"}, {"id": "enterprise_certification_certifier_enterpriseuxcertifier_certify_screen_architecture", "label": "._certify_screen_architecture()", "file_type": "code", "source_file": "E:\\all downloads\\Pharmacy_ERP\\frontend\\enterprise_certification\\certifier.py", "source_location": "L176"}, {"id": "enterprise_certification_certifier_enterpriseuxcertifier_certify_reporting_stability", "label": "._certify_reporting_stability()", "file_type": "code", "source_file": "E:\\all downloads\\Pharmacy_ERP\\frontend\\enterprise_certification\\certifier.py", "source_location": "L224"}, {"id": "enterprise_certification_certifier_enterpriseuxcertifier_certify_visual_maturity", "label": "._certify_visual_maturity()", "file_type": "code", "source_file": "E:\\all downloads\\Pharmacy_ERP\\frontend\\enterprise_certification\\certifier.py", "source_location": "L255"}, {"id": "enterprise_certification_certifier_enterpriseuxcertifier_certify_human_error_resilience", "label": "._certify_human_error_resilience()", "file_type": "code", "source_file": "E:\\all downloads\\Pharmacy_ERP\\frontend\\enterprise_certification\\certifier.py", "source_location": "L286"}, {"id": "enterprise_certification_certifier_enterpriseuxcertifier_certify_performance", "label": "._certify_performance()", "file_type": "code", "source_file": "E:\\all downloads\\Pharmacy_ERP\\frontend\\enterprise_certification\\certifier.py", "source_location": "L321"}, {"id": "enterprise_certification_certifier_enterpriseuxcertifier_certify_workflow_integrity", "label": "._certify_workflow_integrity()", "file_type": "code", "source_file": "E:\\all downloads\\Pharmacy_ERP\\frontend\\enterprise_certification\\certifier.py", "source_location": "L347"}, {"id": "enterprise_certification_certifier_enterpriseuxcertifier_certify", "label": ".certify()", "file_type": "code", "source_file": "E:\\all downloads\\Pharmacy_ERP\\frontend\\enterprise_certification\\certifier.py", "source_location": "L380"}, {"id": "enterprise_certification_certifier_run_certification", "label": "run_certification()", "file_type": "code", "source_file": "E:\\all downloads\\Pharmacy_ERP\\frontend\\enterprise_certification\\certifier.py", "source_location": "L418"}, {"id": "enterprise_certification_certifier_rationale_1", "label": "Enterprise UX + Operational Safety Certifier (Phase D.7).  Static analysis certi", "file_type": "rationale", "source_file": "E:\\all downloads\\Pharmacy_ERP\\frontend\\enterprise_certification\\certifier.py", "source_location": "L1"}, {"id": "enterprise_certification_certifier_rationale_23", "label": "Static analysis certifier for Enterprise UX + Operational Safety.          Certi", "file_type": "rationale", "source_file": "E:\\all downloads\\Pharmacy_ERP\\frontend\\enterprise_certification\\certifier.py", "source_location": "L23"}, {"id": "enterprise_certification_certifier_rationale_287", "label": "Certify human-error resilience by checking all safety mechanisms.         Combin", "file_type": "rationale", "source_file": "E:\\all downloads\\Pharmacy_ERP\\frontend\\enterprise_certification\\certifier.py", "source_location": "L287"}, {"id": "enterprise_certification_certifier_rationale_348", "label": "Verify workflow-related screens and components exist.         Checks for key wor", "file_type": "rationale", "source_file": "E:\\all downloads\\Pharmacy_ERP\\frontend\\enterprise_certification\\certifier.py", "source_location": "L348"}, {"id": "enterprise_certification_certifier_rationale_381", "label": "Run full certification and return structured report.", "file_type": "rationale", "source_file": "E:\\all downloads\\Pharmacy_ERP\\frontend\\enterprise_certification\\certifier.py", "source_location": "L381"}, {"id": "enterprise_certification_certifier_rationale_419", "label": "Run certification and return structured report.", "file_type": "rationale", "source_file": "E:\\all downloads\\Pharmacy_ERP\\frontend\\enterprise_certification\\certifier.py", "source_location": "L419"}], "edges": [{"source": "e_all_downloads_pharmacy_erp_frontend_enterprise_certification_certifier_py", "target": "ast", "relation": "imports", "context": "import", "confidence": "EXTRACTED", "source_file": "E:\\all downloads\\Pharmacy_ERP\\frontend\\enterprise_certification\\certifier.py", "source_location": "L9", "weight": 1.0}, {"source": "e_all_downloads_pharmacy_erp_frontend_enterprise_certification_certifier_py", "target": "os", "relation": "imports", "context": "import", "confidence": "EXTRACTED", "source_file": "E:\\all downloads\\Pharmacy_ERP\\frontend\\enterprise_certification\\certifier.py", "source_location": "L10", "weight": 1.0}, {"source": "e_all_downloads_pharmacy_erp_frontend_enterprise_certification_certifier_py", "target": "re", "relation": "imports", "context": "import", "confidence": "EXTRACTED", "source_file": "E:\\all downloads\\Pharmacy_ERP\\frontend\\enterprise_certification\\certifier.py", "source_location": "L11", "weight": 1.0}, {"source": "e_all_downloads_pharmacy_erp_frontend_enterprise_certification_certifier_py", "target": "typing", "relation": "imports_from", "context": "import", "confidence": "EXTRACTED", "source_file": "E:\\all downloads\\Pharmacy_ERP\\frontend\\enterprise_certification\\certifier.py", "source_location": "L12", "weight": 1.0}, {"source": "e_all_downloads_pharmacy_erp_frontend_enterprise_certification_certifier_py", "target": "enterprise_certification_certifier_enterpriseuxcertifier", "relation": "contains", "confidence": "EXTRACTED", "source_file": "E:\\all downloads\\Pharmacy_ERP\\frontend\\enterprise_certification\\certifier.py", "source_location": "L22", "weight": 1.0}, {"source": "enterprise_certification_certifier_enterpriseuxcertifier", "target": "enterprise_certification_certifier_enterpriseuxcertifier_init", "relation": "method", "confidence": "EXTRACTED", "source_file": "E:\\all downloads\\Pharmacy_ERP\\frontend\\enterprise_certification\\certifier.py", "source_location": "L30", "weight": 1.0}, {"source": "enterprise_certification_certifier_enterpriseuxcertifier", "target": "enterprise_certification_certifier_enterpriseuxcertifier_file_exists", "relation": "method", "confidence": "EXTRACTED", "source_file": "E:\\all downloads\\Pharmacy_ERP\\frontend\\enterprise_certification\\certifier.py", "source_location": "L45", "weight": 1.0}, {"source": "enterprise_certification_certifier_enterpriseuxcertifier_file_exists", "target": "str", "relation": "references", "context": "parameter_type", "confidence": "EXTRACTED", "source_file": "E:\\all downloads\\Pharmacy_ERP\\frontend\\enterprise_certification\\certifier.py", "source_location": "L45", "weight": 1.0}, {"source": "enterprise_certification_certifier_enterpriseuxcertifier_file_exists", "target": "bool", "relation": "references", "context": "return_type", "confidence": "EXTRACTED", "source_file": "E:\\all downloads\\Pharmacy_ERP\\frontend\\enterprise_certification\\certifier.py", "source_location": "L45", "weight": 1.0}, {"source": "enterprise_certification_certifier_enterpriseuxcertifier", "target": "enterprise_certification_certifier_enterpriseuxcertifier_read_file", "relation": "method", "confidence": "EXTRACTED", "source_file": "E:\\all downloads\\Pharmacy_ERP\\frontend\\enterprise_certification\\certifier.py", "source_location": "L48", "weight": 1.0}, {"source": "enterprise_certification_certifier_enterpriseuxcertifier_read_file", "target": "str", "relation": "references", "context": "parameter_type", "confidence": "EXTRACTED", "source_file": "E:\\all downloads\\Pharmacy_ERP\\frontend\\enterprise_certification\\certifier.py", "source_location": "L48", "weight": 1.0}, {"source": "enterprise_certification_certifier_enterpriseuxcertifier_read_file", "target": "str", "relation": "references", "context": "return_type", "confidence": "EXTRACTED", "source_file": "E:\\all downloads\\Pharmacy_ERP\\frontend\\enterprise_certification\\certifier.py", "source_location": "L48", "weight": 1.0}, {"source": "enterprise_certification_certifier_enterpriseuxcertifier", "target": "enterprise_certification_certifier_enterpriseuxcertifier_has_class", "relation": "method", "confidence": "EXTRACTED", "source_file": "E:\\all downloads\\Pharmacy_ERP\\frontend\\enterprise_certification\\certifier.py", "source_location": "L55", "weight": 1.0}, {"source": "enterprise_certification_certifier_enterpriseuxcertifier_has_class", "target": "str", "relation": "references", "context": "parameter_type", "confidence": "EXTRACTED", "source_file": "E:\\all downloads\\Pharmacy_ERP\\frontend\\enterprise_certification\\certifier.py", "source_location": "L55", "weight": 1.0}, {"source": "enterprise_certification_certifier_enterpriseuxcertifier_has_class", "target": "str", "relation": "references", "context": "parameter_type", "confidence": "EXTRACTED", "source_file": "E:\\all downloads\\Pharmacy_ERP\\frontend\\enterprise_certification\\certifier.py", "source_location": "L55", "weight": 1.0}, {"source": "enterprise_certification_certifier_enterpriseuxcertifier_has_class", "target": "bool", "relation": "references", "context": "return_type", "confidence": "EXTRACTED", "source_file": "E:\\all downloads\\Pharmacy_ERP\\frontend\\enterprise_certification\\certifier.py", "source_location": "L55", "weight": 1.0}, {"source": "enterprise_certification_certifier_enterpriseuxcertifier", "target": "enterprise_certification_certifier_enterpriseuxcertifier_has_method", "relation": "method", "confidence": "EXTRACTED", "source_file": "E:\\all downloads\\Pharmacy_ERP\\frontend\\enterprise_certification\\certifier.py", "source_location": "L58", "weight": 1.0}, {"source": "enterprise_certification_certifier_enterpriseuxcertifier_has_method", "target": "str", "relation": "references", "context": "parameter_type", "confidence": "EXTRACTED", "source_file": "E:\\all downloads\\Pharmacy_ERP\\frontend\\enterprise_certification\\certifier.py", "source_location": "L58", "weight": 1.0}, {"source": "enterprise_certification_certifier_enterpriseuxcertifier_has_method", "target": "str", "relation": "references", "context": "parameter_type", "confidence": "EXTRACTED", "source_file": "E:\\all downloads\\Pharmacy_ERP\\frontend\\enterprise_certification\\certifier.py", "source_location": "L58", "weight": 1.0}, {"source": "enterprise_certification_certifier_enterpriseuxcertifier_has_method", "target": "bool", "relation": "references", "context": "return_type", "confidence": "EXTRACTED", "source_file": "E:\\all downloads\\Pharmacy_ERP\\frontend\\enterprise_certification\\certifier.py", "source_location": "L58", "weight": 1.0}, {"source": "enterprise_certification_certifier_enterpriseuxcertifier", "target": "enterprise_certification_certifier_enterpriseuxcertifier_has_import", "relation": "method", "confidence": "EXTRACTED", "source_file": "E:\\all downloads\\Pharmacy_ERP\\frontend\\enterprise_certification\\certifier.py", "source_location": "L61", "weight": 1.0}, {"source": "enterprise_certification_certifier_enterpriseuxcertifier_has_import", "target": "str", "relation": "references", "context": "parameter_type", "confidence": "EXTRACTED", "source_file": "E:\\all downloads\\Pharmacy_ERP\\frontend\\enterprise_certification\\certifier.py", "source_location": "L61", "weight": 1.0}, {"source": "enterprise_certification_certifier_enterpriseuxcertifier_has_import", "target": "str", "relation": "references", "context": "parameter_type", "confidence": "EXTRACTED", "source_file": "E:\\all downloads\\Pharmacy_ERP\\frontend\\enterprise_certification\\certifier.py", "source_location": "L61", "weight": 1.0}, {"source": "enterprise_certification_certifier_enterpriseuxcertifier_has_import", "target": "bool", "relation": "references", "context": "return_type", "confidence": "EXTRACTED", "source_file": "E:\\all downloads\\Pharmacy_ERP\\frontend\\enterprise_certification\\certifier.py", "source_location": "L61", "weight": 1.0}, {"source": "enterprise_certification_certifier_enterpriseuxcertifier", "target": "enterprise_certification_certifier_enterpriseuxcertifier_count_pattern", "relation": "method", "confidence": "EXTRACTED", "source_file": "E:\\all downloads\\Pharmacy_ERP\\frontend\\enterprise_certification\\certifier.py", "source_location": "L64", "weight": 1.0}, {"source": "enterprise_certification_certifier_enterpriseuxcertifier_count_pattern", "target": "str", "relation": "references", "context": "parameter_type", "confidence": "EXTRACTED", "source_file": "E:\\all downloads\\Pharmacy_ERP\\frontend\\enterprise_certification\\certifier.py", "source_location": "L64", "weight": 1.0}, {"source": "enterprise_certification_certifier_enterpriseuxcertifier_count_pattern", "target": "str", "relation": "references", "context": "parameter_type", "confidence": "EXTRACTED", "source_file": "E:\\all downloads\\Pharmacy_ERP\\frontend\\enterprise_certification\\certifier.py", "source_location": "L64", "weight": 1.0}, {"source": "enterprise_certification_certifier_enterpriseuxcertifier_count_pattern", "target": "int", "relation": "references", "context": "return_type", "confidence": "EXTRACTED", "source_file": "E:\\all downloads\\Pharmacy_ERP\\frontend\\enterprise_certification\\certifier.py", "source_location": "L64", "weight": 1.0}, {"source": "enterprise_certification_certifier_enterpriseuxcertifier", "target": "enterprise_certification_certifier_enterpriseuxcertifier_score_boolean", "relation": "method", "confidence": "EXTRACTED", "source_file": "E:\\all downloads\\Pharmacy_ERP\\frontend\\enterprise_certification\\certifier.py", "source_location": "L67", "weight": 1.0}, {"source": "enterprise_certification_certifier_enterpriseuxcertifier_score_boolean", "target": "bool", "relation": "references", "context": "parameter_type", "confidence": "EXTRACTED", "source_file": "E:\\all downloads\\Pharmacy_ERP\\frontend\\enterprise_certification\\certifier.py", "source_location": "L67", "weight": 1.0}, {"source": "enterprise_certification_certifier_enterpriseuxcertifier_score_boolean", "target": "str", "relation": "references", "context": "return_type", "confidence": "EXTRACTED", "source_file": "E:\\all downloads\\Pharmacy_ERP\\frontend\\enterprise_certification\\certifier.py", "source_location": "L67", "weight": 1.0}, {"source": "enterprise_certification_certifier_enterpriseuxcertifier", "target": "enterprise_certification_certifier_enterpriseuxcertifier_certify_form_system", "relation": "method", "confidence": "EXTRACTED", "source_file": "E:\\all downloads\\Pharmacy_ERP\\frontend\\enterprise_certification\\certifier.py", "source_location": "L72", "weight": 1.0}, {"source": "enterprise_certification_certifier_enterpriseuxcertifier_certify_form_system", "target": "str", "relation": "references", "context": "generic_arg", "confidence": "EXTRACTED", "source_file": "E:\\all downloads\\Pharmacy_ERP\\frontend\\enterprise_certification\\certifier.py", "source_location": "L72", "weight": 1.0}, {"source": "enterprise_certification_certifier_enterpriseuxcertifier_certify_form_system", "target": "str", "relation": "references", "context": "generic_arg", "confidence": "EXTRACTED", "source_file": "E:\\all downloads\\Pharmacy_ERP\\frontend\\enterprise_certification\\certifier.py", "source_location": "L72", "weight": 1.0}, {"source": "enterprise_certification_certifier_enterpriseuxcertifier_certify_form_system", "target": "any", "relation": "references", "context": "generic_arg", "confidence": "EXTRACTED", "source_file": "E:\\all downloads\\Pharmacy_ERP\\frontend\\enterprise_certification\\certifier.py", "source_location": "L72", "weight": 1.0}, {"source": "enterprise_certification_certifier_enterpriseuxcertifier", "target": "enterprise_certification_certifier_enterpriseuxcertifier_certify_table_system", "relation": "method", "confidence": "EXTRACTED", "source_file": "E:\\all downloads\\Pharmacy_ERP\\frontend\\enterprise_certification\\certifier.py", "source_location": "L102", "weight": 1.0}, {"source": "enterprise_certification_certifier_enterpriseuxcertifier_certify_table_system", "target": "str", "relation": "references", "context": "generic_arg", "confidence": "EXTRACTED", "source_file": "E:\\all downloads\\Pharmacy_ERP\\frontend\\enterprise_certification\\certifier.py", "source_location": "L102", "weight": 1.0}, {"source": "enterprise_certification_certifier_enterpriseuxcertifier_certify_table_system", "target": "str", "relation": "references", "context": "generic_arg", "confidence": "EXTRACTED", "source_file": "E:\\all downloads\\Pharmacy_ERP\\frontend\\enterprise_certification\\certifier.py", "source_location": "L102", "weight": 1.0}, {"source": "enterprise_certification_certifier_enterpriseuxcertifier_certify_table_system", "target": "any", "relation": "references", "context": "generic_arg", "confidence": "EXTRACTED", "source_file": "E:\\all downloads\\Pharmacy_ERP\\frontend\\enterprise_certification\\certifier.py", "source_location": "L102", "weight": 1.0}, {"source": "enterprise_certification_certifier_enterpriseuxcertifier", "target": "enterprise_certification_certifier_enterpriseuxcertifier_certify_operator_safety", "relation": "method", "confidence": "EXTRACTED", "source_file": "E:\\all downloads\\Pharmacy_ERP\\frontend\\enterprise_certification\\certifier.py", "source_location": "L133", "weight": 1.0}, {"source": "enterprise_certification_certifier_enterpriseuxcertifier_certify_operator_safety", "target": "str", "relation": "references", "context": "generic_arg", "confidence": "EXTRACTED", "source_file": "E:\\all downloads\\Pharmacy_ERP\\frontend\\enterprise_certification\\certifier.py", "source_location": "L133", "weight": 1.0}, {"source": "enterprise_certification_certifier_enterpriseuxcertifier_certify_operator_safety", "target": "str", "relation": "references", "context": "generic_arg", "confidence": "EXTRACTED", "source_file": "E:\\all downloads\\Pharmacy_ERP\\frontend\\enterprise_certification\\certifier.py", "source_location": "L133", "weight": 1.0}, {"source": "enterprise_certification_certifier_enterpriseuxcertifier_certify_operator_safety", "target": "any", "relation": "references", "context": "generic_arg", "confidence": "EXTRACTED", "source_file": "E:\\all downloads\\Pharmacy_ERP\\frontend\\enterprise_certification\\certifier.py", "source_location": "L133", "weight": 1.0}, {"source": "enterprise_certification_certifier_enterpriseuxcertifier", "target": "enterprise_certification_certifier_enterpriseuxcertifier_certify_screen_architecture", "relation": "method", "confidence": "EXTRACTED", "source_file": "E:\\all downloads\\Pharmacy_ERP\\frontend\\enterprise_certification\\certifier.py", "source_location": "L176", "weight": 1.0}, {"source": "enterprise_certification_certifier_enterpriseuxcertifier_certify_screen_architecture", "target": "str", "relation": "references", "context": "generic_arg", "confidence": "EXTRACTED", "source_file": "E:\\all downloads\\Pharmacy_ERP\\frontend\\enterprise_certification\\certifier.py", "source_location": "L176", "weight": 1.0}, {"source": "enterprise_certification_certifier_enterpriseuxcertifier_certify_screen_architecture", "target": "str", "relation": "references", "context": "generic_arg", "confidence": "EXTRACTED", "source_file": "E:\\all downloads\\Pharmacy_ERP\\frontend\\enterprise_certification\\certifier.py", "source_location": "L176", "weight": 1.0}, {"source": "enterprise_certification_certifier_enterpriseuxcertifier_certify_screen_architecture", "target": "any", "relation": "references", "context": "generic_arg", "confidence": "EXTRACTED", "source_file": "E:\\all downloads\\Pharmacy_ERP\\frontend\\enterprise_certification\\certifier.py", "source_location": "L176", "weight": 1.0}, {"source": "enterprise_certification_certifier_enterpriseuxcertifier", "target": "enterprise_certification_certifier_enterpriseuxcertifier_certify_reporting_stability", "relation": "method", "confidence": "EXTRACTED", "source_file": "E:\\all downloads\\Pharmacy_ERP\\frontend\\enterprise_certification\\certifier.py", "source_location": "L224", "weight": 1.0}, {"source": "enterprise_certification_certifier_enterpriseuxcertifier_certify_reporting_stability", "target": "str", "relation": "references", "context": "generic_arg", "confidence": "EXTRACTED", "source_file": "E:\\all downloads\\Pharmacy_ERP\\frontend\\enterprise_certification\\certifier.py", "source_location": "L224", "weight": 1.0}, {"source": "enterprise_certification_certifier_enterpriseuxcertifier_certify_reporting_stability", "target": "str", "relation": "references", "context": "generic_arg", "confidence": "EXTRACTED", "source_file": "E:\\all downloads\\Pharmacy_ERP\\frontend\\enterprise_certification\\certifier.py", "source_location": "L224", "weight": 1.0}, {"source": "enterprise_certification_certifier_enterpriseuxcertifier_certify_reporting_stability", "target": "any", "relation": "references", "context": "generic_arg", "confidence": "EXTRACTED", "source_file": "E:\\all downloads\\Pharmacy_ERP\\frontend\\enterprise_certification\\certifier.py", "source_location": "L224", "weight": 1.0}, {"source": "enterprise_certification_certifier_enterpriseuxcertifier", "target": "enterprise_certification_certifier_enterpriseuxcertifier_certify_visual_maturity", "relation": "method", "confidence": "EXTRACTED", "source_file": "E:\\all downloads\\Pharmacy_ERP\\frontend\\enterprise_certification\\certifier.py", "source_location": "L255", "weight": 1.0}, {"source": "enterprise_certification_certifier_enterpriseuxcertifier_certify_visual_maturity", "target": "str", "relation": "references", "context": "generic_arg", "confidence": "EXTRACTED", "source_file": "E:\\all downloads\\Pharmacy_ERP\\frontend\\enterprise_certification\\certifier.py", "source_location": "L255", "weight": 1.0}, {"source": "enterprise_certification_certifier_enterpriseuxcertifier_certify_visual_maturity", "target": "str", "relation": "references", "context": "generic_arg", "confidence": "EXTRACTED", "source_file": "E:\\all downloads\\Pharmacy_ERP\\frontend\\enterprise_certification\\certifier.py", "source_location": "L255", "weight": 1.0}, {"source": "enterprise_certification_certifier_enterpriseuxcertifier_certify_visual_maturity", "target": "any", "relation": "references", "context": "generic_arg", "confidence": "EXTRACTED", "source_file": "E:\\all downloads\\Pharmacy_ERP\\frontend\\enterprise_certification\\certifier.py", "source_location": "L255", "weight": 1.0}, {"source": "enterprise_certification_certifier_enterpriseuxcertifier", "target": "enterprise_certification_certifier_enterpriseuxcertifier_certify_human_error_resilience", "relation": "method", "confidence": "EXTRACTED", "source_file": "E:\\all downloads\\Pharmacy_ERP\\frontend\\enterprise_certification\\certifier.py", "source_location": "L286", "weight": 1.0}, {"source": "enterprise_certification_certifier_enterpriseuxcertifier_certify_human_error_resilience", "target": "str", "relation": "references", "context": "generic_arg", "confidence": "EXTRACTED", "source_file": "E:\\all downloads\\Pharmacy_ERP\\frontend\\enterprise_certification\\certifier.py", "source_location": "L286", "weight": 1.0}, {"source": "enterprise_certification_certifier_enterpriseuxcertifier_certify_human_error_resilience", "target": "str", "relation": "references", "context": "generic_arg", "confidence": "EXTRACTED", "source_file": "E:\\all downloads\\Pharmacy_ERP\\frontend\\enterprise_certification\\certifier.py", "source_location": "L286", "weight": 1.0}, {"source": "enterprise_certification_certifier_enterpriseuxcertifier_certify_human_error_resilience", "target": "any", "relation": "references", "context": "generic_arg", "confidence": "EXTRACTED", "source_file": "E:\\all downloads\\Pharmacy_ERP\\frontend\\enterprise_certification\\certifier.py", "source_location": "L286", "weight": 1.0}, {"source": "enterprise_certification_certifier_enterpriseuxcertifier", "target": "enterprise_certification_certifier_enterpriseuxcertifier_certify_performance", "relation": "method", "confidence": "EXTRACTED", "source_file": "E:\\all downloads\\Pharmacy_ERP\\frontend\\enterprise_certification\\certifier.py", "source_location": "L321", "weight": 1.0}, {"source": "enterprise_certification_certifier_enterpriseuxcertifier_certify_performance", "target": "str", "relation": "references", "context": "generic_arg", "confidence": "EXTRACTED", "source_file": "E:\\all downloads\\Pharmacy_ERP\\frontend\\enterprise_certification\\certifier.py", "source_location": "L321", "weight": 1.0}, {"source": "enterprise_certification_certifier_enterpriseuxcertifier_certify_performance", "target": "str", "relation": "references", "context": "generic_arg", "confidence": "EXTRACTED", "source_file": "E:\\all downloads\\Pharmacy_ERP\\frontend\\enterprise_certification\\certifier.py", "source_location": "L321", "weight": 1.0}, {"source": "enterprise_certification_certifier_enterpriseuxcertifier_certify_performance", "target": "any", "relation": "references", "context": "generic_arg", "confidence": "EXTRACTED", "source_file": "E:\\all downloads\\Pharmacy_ERP\\frontend\\enterprise_certification\\certifier.py", "source_location": "L321", "weight": 1.0}, {"source": "enterprise_certification_certifier_enterpriseuxcertifier", "target": "enterprise_certification_certifier_enterpriseuxcertifier_certify_workflow_integrity", "relation": "method", "confidence": "EXTRACTED", "source_file": "E:\\all downloads\\Pharmacy_ERP\\frontend\\enterprise_certification\\certifier.py", "source_location": "L347", "weight": 1.0}, {"source": "enterprise_certification_certifier_enterpriseuxcertifier_certify_workflow_integrity", "target": "str", "relation": "references", "context": "generic_arg", "confidence": "EXTRACTED", "source_file": "E:\\all downloads\\Pharmacy_ERP\\frontend\\enterprise_certification\\certifier.py", "source_location": "L347", "weight": 1.0}, {"source": "enterprise_certification_certifier_enterpriseuxcertifier_certify_workflow_integrity", "target": "str", "relation": "references", "context": "generic_arg", "confidence": "EXTRACTED", "source_file": "E:\\all downloads\\Pharmacy_ERP\\frontend\\enterprise_certification\\certifier.py", "source_location": "L347", "weight": 1.0}, {"source": "enterprise_certification_certifier_enterpriseuxcertifier_certify_workflow_integrity", "target": "any", "relation": "references", "context": "generic_arg", "confidence": "EXTRACTED", "source_file": "E:\\all downloads\\Pharmacy_ERP\\frontend\\enterprise_certification\\certifier.py", "source_location": "L347", "weight": 1.0}, {"source": "enterprise_certification_certifier_enterpriseuxcertifier", "target": "enterprise_certification_certifier_enterpriseuxcertifier_certify", "relation": "method", "confidence": "EXTRACTED", "source_file": "E:\\all downloads\\Pharmacy_ERP\\frontend\\enterprise_certification\\certifier.py", "source_location": "L380", "weight": 1.0}, {"source": "enterprise_certification_certifier_enterpriseuxcertifier_certify", "target": "str", "relation": "references", "context": "generic_arg", "confidence": "EXTRACTED", "source_file": "E:\\all downloads\\Pharmacy_ERP\\frontend\\enterprise_certification\\certifier.py", "source_location": "L380", "weight": 1.0}, {"source": "enterprise_certification_certifier_enterpriseuxcertifier_certify", "target": "any", "relation": "references", "context": "generic_arg", "confidence": "EXTRACTED", "source_file": "E:\\all downloads\\Pharmacy_ERP\\frontend\\enterprise_certification\\certifier.py", "source_location": "L380", "weight": 1.0}, {"source": "e_all_downloads_pharmacy_erp_frontend_enterprise_certification_certifier_py", "target": "enterprise_certification_certifier_run_certification", "relation": "contains", "confidence": "EXTRACTED", "source_file": "E:\\all downloads\\Pharmacy_ERP\\frontend\\enterprise_certification\\certifier.py", "source_location": "L418", "weight": 1.0}, {"source": "enterprise_certification_certifier_run_certification", "target": "str", "relation": "references", "context": "generic_arg", "confidence": "EXTRACTED", "source_file": "E:\\all downloads\\Pharmacy_ERP\\frontend\\enterprise_certification\\certifier.py", "source_location": "L418", "weight": 1.0}, {"source": "enterprise_certification_certifier_run_certification", "target": "any", "relation": "references", "context": "generic_arg", "confidence": "EXTRACTED", "source_file": "E:\\all downloads\\Pharmacy_ERP\\frontend\\enterprise_certification\\certifier.py", "source_location": "L418", "weight": 1.0}, {"source": "e_all_downloads_pharmacy_erp_frontend_enterprise_certification_certifier_py", "target": "json", "relation": "imports", "context": "import", "confidence": "EXTRACTED", "source_file": "E:\\all downloads\\Pharmacy_ERP\\frontend\\enterprise_certification\\certifier.py", "source_location": "L425", "weight": 1.0}, {"source": "enterprise_certification_certifier_enterpriseuxcertifier_certify_form_system", "target": "enterprise_certification_certifier_enterpriseuxcertifier_read_file", "relation": "calls", "context": "call", "confidence": "EXTRACTED", "source_file": "E:\\all downloads\\Pharmacy_ERP\\frontend\\enterprise_certification\\certifier.py", "source_location": "L74", "weight": 1.0}, {"source": "enterprise_certification_certifier_enterpriseuxcertifier_certify_form_system", "target": "enterprise_certification_certifier_enterpriseuxcertifier_has_class", "relation": "calls", "context": "call", "confidence": "EXTRACTED", "source_file": "E:\\all downloads\\Pharmacy_ERP\\frontend\\enterprise_certification\\certifier.py", "source_location": "L77", "weight": 1.0}, {"source": "enterprise_certification_certifier_enterpriseuxcertifier_certify_form_system", "target": "enterprise_certification_certifier_enterpriseuxcertifier_has_method", "relation": "calls", "context": "call", "confidence": "EXTRACTED", "source_file": "E:\\all downloads\\Pharmacy_ERP\\frontend\\enterprise_certification\\certifier.py", "source_location": "L78", "weight": 1.0}, {"source": "enterprise_certification_certifier_enterpriseuxcertifier_certify_table_system", "target": "enterprise_certification_certifier_enterpriseuxcertifier_read_file", "relation": "calls", "context": "call", "confidence": "EXTRACTED", "source_file": "E:\\all downloads\\Pharmacy_ERP\\frontend\\enterprise_certification\\certifier.py", "source_location": "L104", "weight": 1.0}, {"source": "enterprise_certification_certifier_enterpriseuxcertifier_certify_table_system", "target": "enterprise_certification_certifier_enterpriseuxcertifier_has_class", "relation": "calls", "context": "call", "confidence": "EXTRACTED", "source_file": "E:\\all downloads\\Pharmacy_ERP\\frontend\\enterprise_certification\\certifier.py", "source_location": "L107", "weight": 1.0}, {"source": "enterprise_certification_certifier_enterpriseuxcertifier_certify_table_system", "target": "enterprise_certification_certifier_enterpriseuxcertifier_has_method", "relation": "calls", "context": "call", "confidence": "EXTRACTED", "source_file": "E:\\all downloads\\Pharmacy_ERP\\frontend\\enterprise_certification\\certifier.py", "source_location": "L116", "weight": 1.0}, {"source": "enterprise_certification_certifier_enterpriseuxcertifier_certify_operator_safety", "target": "enterprise_certification_certifier_enterpriseuxcertifier_read_file", "relation": "calls", "context": "call", "confidence": "EXTRACTED", "source_file": "E:\\all downloads\\Pharmacy_ERP\\frontend\\enterprise_certification\\certifier.py", "source_location": "L135", "weight": 1.0}, {"source": "enterprise_certification_certifier_enterpriseuxcertifier_certify_operator_safety", "target": "enterprise_certification_certifier_enterpriseuxcertifier_has_class", "relation": "calls", "context": "call", "confidence": "EXTRACTED", "source_file": "E:\\all downloads\\Pharmacy_ERP\\frontend\\enterprise_certification\\certifier.py", "source_location": "L141", "weight": 1.0}, {"source": "enterprise_certification_certifier_enterpriseuxcertifier_certify_operator_safety", "target": "enterprise_certification_certifier_enterpriseuxcertifier_has_method", "relation": "calls", "context": "call", "confidence": "EXTRACTED", "source_file": "E:\\all downloads\\Pharmacy_ERP\\frontend\\enterprise_certification\\certifier.py", "source_location": "L154", "weight": 1.0}, {"source": "enterprise_certification_certifier_enterpriseuxcertifier_certify_screen_architecture", "target": "enterprise_certification_certifier_enterpriseuxcertifier_read_file", "relation": "calls", "context": "call", "confidence": "EXTRACTED", "source_file": "E:\\all downloads\\Pharmacy_ERP\\frontend\\enterprise_certification\\certifier.py", "source_location": "L178", "weight": 1.0}, {"source": "enterprise_certification_certifier_enterpriseuxcertifier_certify_screen_architecture", "target": "enterprise_certification_certifier_enterpriseuxcertifier_has_class", "relation": "calls", "context": "call", "confidence": "EXTRACTED", "source_file": "E:\\all downloads\\Pharmacy_ERP\\frontend\\enterprise_certification\\certifier.py", "source_location": "L181", "weight": 1.0}, {"source": "enterprise_certification_certifier_enterpriseuxcertifier_certify_screen_architecture", "target": "enterprise_certification_certifier_enterpriseuxcertifier_has_method", "relation": "calls", "context": "call", "confidence": "EXTRACTED", "source_file": "E:\\all downloads\\Pharmacy_ERP\\frontend\\enterprise_certification\\certifier.py", "source_location": "L184", "weight": 1.0}, {"source": "enterprise_certification_certifier_enterpriseuxcertifier_certify_reporting_stability", "target": "enterprise_certification_certifier_enterpriseuxcertifier_read_file", "relation": "calls", "context": "call", "confidence": "EXTRACTED", "source_file": "E:\\all downloads\\Pharmacy_ERP\\frontend\\enterprise_certification\\certifier.py", "source_location": "L226", "weight": 1.0}, {"source": "enterprise_certification_certifier_enterpriseuxcertifier_certify_reporting_stability", "target": "enterprise_certification_certifier_enterpriseuxcertifier_has_class", "relation": "calls", "context": "call", "confidence": "EXTRACTED", "source_file": "E:\\all downloads\\Pharmacy_ERP\\frontend\\enterprise_certification\\certifier.py", "source_location": "L232", "weight": 1.0}, {"source": "enterprise_certification_certifier_enterpriseuxcertifier_certify_visual_maturity", "target": "enterprise_certification_certifier_enterpriseuxcertifier_read_file", "relation": "calls", "context": "call", "confidence": "EXTRACTED", "source_file": "E:\\all downloads\\Pharmacy_ERP\\frontend\\enterprise_certification\\certifier.py", "source_location": "L257", "weight": 1.0}, {"source": "enterprise_certification_certifier_enterpriseuxcertifier_certify_visual_maturity", "target": "enterprise_certification_certifier_enterpriseuxcertifier_has_class", "relation": "calls", "context": "call", "confidence": "EXTRACTED", "source_file": "E:\\all downloads\\Pharmacy_ERP\\frontend\\enterprise_certification\\certifier.py", "source_location": "L264", "weight": 1.0}, {"source": "enterprise_certification_certifier_enterpriseuxcertifier_certify_human_error_resilience", "target": "enterprise_certification_certifier_enterpriseuxcertifier_read_file", "relation": "calls", "context": "call", "confidence": "EXTRACTED", "source_file": "E:\\all downloads\\Pharmacy_ERP\\frontend\\enterprise_certification\\certifier.py", "source_location": "L292", "weight": 1.0}, {"source": "enterprise_certification_certifier_enterpriseuxcertifier_certify_performance", "target": "enterprise_certification_certifier_enterpriseuxcertifier_file_exists", "relation": "calls", "context": "call", "confidence": "EXTRACTED", "source_file": "E:\\all downloads\\Pharmacy_ERP\\frontend\\enterprise_certification\\certifier.py", "source_location": "L326", "weight": 1.0}, {"source": "enterprise_certification_certifier_enterpriseuxcertifier_certify_performance", "target": "enterprise_certification_certifier_enterpriseuxcertifier_read_file", "relation": "calls", "context": "call", "confidence": "EXTRACTED", "source_file": "E:\\all downloads\\Pharmacy_ERP\\frontend\\enterprise_certification\\certifier.py", "source_location": "L330", "weight": 1.0}, {"source": "enterprise_certification_certifier_run_certification", "target": "enterprise_certification_certifier_enterpriseuxcertifier", "relation": "calls", "context": "call", "confidence": "EXTRACTED", "source_file": "E:\\all downloads\\Pharmacy_ERP\\frontend\\enterprise_certification\\certifier.py", "source_location": "L420", "weight": 1.0}, {"source": "enterprise_certification_certifier_run_certification", "target": "enterprise_certification_certifier_enterpriseuxcertifier_certify", "relation": "calls", "context": "call", "confidence": "EXTRACTED", "source_file": "E:\\all downloads\\Pharmacy_ERP\\frontend\\enterprise_certification\\certifier.py", "source_location": "L421", "weight": 1.0}, {"source": "enterprise_certification_certifier_rationale_1", "target": "e_all_downloads_pharmacy_erp_frontend_enterprise_certification_certifier_py", "relation": "rationale_for", "confidence": "EXTRACTED", "source_file": "E:\\all downloads\\Pharmacy_ERP\\frontend\\enterprise_certification\\certifier.py", "source_location": "L1", "weight": 1.0}, {"source": "enterprise_certification_certifier_rationale_23", "target": "enterprise_certification_certifier_enterpriseuxcertifier", "relation": "rationale_for", "confidence": "EXTRACTED", "source_file": "E:\\all downloads\\Pharmacy_ERP\\frontend\\enterprise_certification\\certifier.py", "source_location": "L23", "weight": 1.0}, {"source": "enterprise_certification_certifier_rationale_287", "target": "enterprise_certification_certifier_enterpriseuxcertifier_certify_human_error_resilience", "relation": "rationale_for", "confidence": "EXTRACTED", "source_file": "E:\\all downloads\\Pharmacy_ERP\\frontend\\enterprise_certification\\certifier.py", "source_location": "L287", "weight": 1.0}, {"source": "enterprise_certification_certifier_rationale_348", "target": "enterprise_certification_certifier_enterpriseuxcertifier_certify_workflow_integrity", "relation": "rationale_for", "confidence": "EXTRACTED", "source_file": "E:\\all downloads\\Pharmacy_ERP\\frontend\\enterprise_certification\\certifier.py", "source_location": "L348", "weight": 1.0}, {"source": "enterprise_certification_certifier_rationale_381", "target": "enterprise_certification_certifier_enterpriseuxcertifier_certify", "relation": "rationale_for", "confidence": "EXTRACTED", "source_file": "E:\\all downloads\\Pharmacy_ERP\\frontend\\enterprise_certification\\certifier.py", "source_location": "L381", "weight": 1.0}, {"source": "enterprise_certification_certifier_rationale_419", "target": "enterprise_certification_certifier_run_certification", "relation": "rationale_for", "confidence": "EXTRACTED", "source_file": "E:\\all downloads\\Pharmacy_ERP\\frontend\\enterprise_certification\\certifier.py", "source_location": "L419", "weight": 1.0}], "raw_calls": [{"caller_nid": "enterprise_certification_certifier_enterpriseuxcertifier_file_exists", "callee": "exists", "is_member_call": true, "source_file": "E:\\all downloads\\Pharmacy_ERP\\frontend\\enterprise_certification\\certifier.py", "source_location": "L46"}, {"caller_nid": "enterprise_certification_certifier_enterpriseuxcertifier_file_exists", "callee": "join", "is_member_call": true, "source_file": "E:\\all downloads\\Pharmacy_ERP\\frontend\\enterprise_certification\\certifier.py", "source_location": "L46"}, {"caller_nid": "enterprise_certification_certifier_enterpriseuxcertifier_read_file", "callee": "join", "is_member_call": true, "source_file": "E:\\all downloads\\Pharmacy_ERP\\frontend\\enterprise_certification\\certifier.py", "source_location": "L49"}, {"caller_nid": "enterprise_certification_certifier_enterpriseuxcertifier_read_file", "callee": "exists", "is_member_call": true, "source_file": "E:\\all downloads\\Pharmacy_ERP\\frontend\\enterprise_certification\\certifier.py", "source_location": "L50"}, {"caller_nid": "enterprise_certification_certifier_enterpriseuxcertifier_read_file", "callee": "read", "is_member_call": true, "source_file": "E:\\all downloads\\Pharmacy_ERP\\frontend\\enterprise_certification\\certifier.py", "source_location": "L52"}, {"caller_nid": "enterprise_certification_certifier_enterpriseuxcertifier_has_class", "callee": "search", "is_member_call": true, "source_file": "E:\\all downloads\\Pharmacy_ERP\\frontend\\enterprise_certification\\certifier.py", "source_location": "L56"}, {"caller_nid": "enterprise_certification_certifier_enterpriseuxcertifier_has_method", "callee": "search", "is_member_call": true, "source_file": "E:\\all downloads\\Pharmacy_ERP\\frontend\\enterprise_certification\\certifier.py", "source_location": "L59"}, {"caller_nid": "enterprise_certification_certifier_enterpriseuxcertifier_count_pattern", "callee": "findall", "is_member_call": true, "source_file": "E:\\all downloads\\Pharmacy_ERP\\frontend\\enterprise_certification\\certifier.py", "source_location": "L65"}, {"caller_nid": "enterprise_certification_certifier_enterpriseuxcertifier_certify_form_system", "callee": "values", "is_member_call": true, "source_file": "E:\\all downloads\\Pharmacy_ERP\\frontend\\enterprise_certification\\certifier.py", "source_location": "L90"}, {"caller_nid": "enterprise_certification_certifier_enterpriseuxcertifier_certify_table_system", "callee": "values", "is_member_call": true, "source_file": "E:\\all downloads\\Pharmacy_ERP\\frontend\\enterprise_certification\\certifier.py", "source_location": "L121"}, {"caller_nid": "enterprise_certification_certifier_enterpriseuxcertifier_certify_operator_safety", "callee": "values", "is_member_call": true, "source_file": "E:\\all downloads\\Pharmacy_ERP\\frontend\\enterprise_certification\\certifier.py", "source_location": "L164"}, {"caller_nid": "enterprise_certification_certifier_enterpriseuxcertifier_certify_screen_architecture", "callee": "walk", "is_member_call": true, "source_file": "E:\\all downloads\\Pharmacy_ERP\\frontend\\enterprise_certification\\certifier.py", "source_location": "L197"}, {"caller_nid": "enterprise_certification_certifier_enterpriseuxcertifier_certify_screen_architecture", "callee": "endswith", "is_member_call": true, "source_file": "E:\\all downloads\\Pharmacy_ERP\\frontend\\enterprise_certification\\certifier.py", "source_location": "L199"}, {"caller_nid": "enterprise_certification_certifier_enterpriseuxcertifier_certify_screen_architecture", "callee": "startswith", "is_member_call": true, "source_file": "E:\\all downloads\\Pharmacy_ERP\\frontend\\enterprise_certification\\certifier.py", "source_location": "L199"}, {"caller_nid": "enterprise_certification_certifier_enterpriseuxcertifier_certify_screen_architecture", "callee": "append", "is_member_call": true, "source_file": "E:\\all downloads\\Pharmacy_ERP\\frontend\\enterprise_certification\\certifier.py", "source_location": "L200"}, {"caller_nid": "enterprise_certification_certifier_enterpriseuxcertifier_certify_screen_architecture", "callee": "join", "is_member_call": true, "source_file": "E:\\all downloads\\Pharmacy_ERP\\frontend\\enterprise_certification\\certifier.py", "source_location": "L200"}, {"caller_nid": "enterprise_certification_certifier_enterpriseuxcertifier_certify_screen_architecture", "callee": "search", "is_member_call": true, "source_file": "E:\\all downloads\\Pharmacy_ERP\\frontend\\enterprise_certification\\certifier.py", "source_location": "L205"}, {"caller_nid": "enterprise_certification_certifier_enterpriseuxcertifier_certify_screen_architecture", "callee": "values", "is_member_call": true, "source_file": "E:\\all downloads\\Pharmacy_ERP\\frontend\\enterprise_certification\\certifier.py", "source_location": "L212"}, {"caller_nid": "enterprise_certification_certifier_enterpriseuxcertifier_certify_reporting_stability", "callee": "join", "is_member_call": true, "source_file": "E:\\all downloads\\Pharmacy_ERP\\frontend\\enterprise_certification\\certifier.py", "source_location": "L226"}, {"caller_nid": "enterprise_certification_certifier_enterpriseuxcertifier_certify_reporting_stability", "callee": "values", "is_member_call": true, "source_file": "E:\\all downloads\\Pharmacy_ERP\\frontend\\enterprise_certification\\certifier.py", "source_location": "L243"}, {"caller_nid": "enterprise_certification_certifier_enterpriseuxcertifier_certify_visual_maturity", "callee": "join", "is_member_call": true, "source_file": "E:\\all downloads\\Pharmacy_ERP\\frontend\\enterprise_certification\\certifier.py", "source_location": "L257"}, {"caller_nid": "enterprise_certification_certifier_enterpriseuxcertifier_certify_visual_maturity", "callee": "values", "is_member_call": true, "source_file": "E:\\all downloads\\Pharmacy_ERP\\frontend\\enterprise_certification\\certifier.py", "source_location": "L274"}, {"caller_nid": "enterprise_certification_certifier_enterpriseuxcertifier_certify_human_error_resilience", "callee": "values", "is_member_call": true, "source_file": "E:\\all downloads\\Pharmacy_ERP\\frontend\\enterprise_certification\\certifier.py", "source_location": "L309"}, {"caller_nid": "enterprise_certification_certifier_enterpriseuxcertifier_certify_performance", "callee": "values", "is_member_call": true, "source_file": "E:\\all downloads\\Pharmacy_ERP\\frontend\\enterprise_certification\\certifier.py", "source_location": "L335"}, {"caller_nid": "enterprise_certification_certifier_enterpriseuxcertifier_certify_workflow_integrity", "callee": "items", "is_member_call": true, "source_file": "E:\\all downloads\\Pharmacy_ERP\\frontend\\enterprise_certification\\certifier.py", "source_location": "L365"}, {"caller_nid": "enterprise_certification_certifier_enterpriseuxcertifier_certify_workflow_integrity", "callee": "join", "is_member_call": true, "source_file": "E:\\all downloads\\Pharmacy_ERP\\frontend\\enterprise_certification\\certifier.py", "source_location": "L366"}, {"caller_nid": "enterprise_certification_certifier_enterpriseuxcertifier_certify_workflow_integrity", "callee": "exists", "is_member_call": true, "source_file": "E:\\all downloads\\Pharmacy_ERP\\frontend\\enterprise_certification\\certifier.py", "source_location": "L369"}, {"caller_nid": "enterprise_certification_certifier_enterpriseuxcertifier_certify_workflow_integrity", "callee": "join", "is_member_call": true, "source_file": "E:\\all downloads\\Pharmacy_ERP\\frontend\\enterprise_certification\\certifier.py", "source_location": "L369"}, {"caller_nid": "enterprise_certification_certifier_enterpriseuxcertifier_certify", "callee": "certifier", "is_member_call": false, "source_file": "E:\\all downloads\\Pharmacy_ERP\\frontend\\enterprise_certification\\certifier.py", "source_location": "L396"}, {"caller_nid": "enterprise_certification_certifier_enterpriseuxcertifier_certify", "callee": "append", "is_member_call": true, "source_file": "E:\\all downloads\\Pharmacy_ERP\\frontend\\enterprise_certification\\certifier.py", "source_location": "L399"}, {"caller_nid": "enterprise_certification_certifier_enterpriseuxcertifier_certify", "callee": "get", "is_member_call": true, "source_file": "E:\\all downloads\\Pharmacy_ERP\\frontend\\enterprise_certification\\certifier.py", "source_location": "L399"}]}