{"nodes": [{"id": "e_all_downloads_pharmacy_erp_backend_core_import_views_py", "label": "import_views.py", "file_type": "code", "source_file": "E:\\all downloads\\Pharmacy_ERP\\backend\\core\\import_views.py", "source_location": "L1"}, {"id": "core_import_views_import_dry_run", "label": "import_dry_run()", "file_type": "code", "source_file": "E:\\all downloads\\Pharmacy_ERP\\backend\\core\\import_views.py", "source_location": "L14"}, {"id": "core_import_views_import_execute", "label": "import_execute()", "file_type": "code", "source_file": "E:\\all downloads\\Pharmacy_ERP\\backend\\core\\import_views.py", "source_location": "L59"}, {"id": "core_import_views_detect_format", "label": "_detect_format()", "file_type": "code", "source_file": "E:\\all downloads\\Pharmacy_ERP\\backend\\core\\import_views.py", "source_location": "L93"}, {"id": "str", "label": "str", "file_type": "code", "source_file": "E:\\all downloads\\Pharmacy_ERP\\backend\\core\\import_views.py", "source_location": "L93"}, {"id": "core_import_views_rationale_1", "label": "Bulk import API views for Pharmacy ERP.", "file_type": "rationale", "source_file": "E:\\all downloads\\Pharmacy_ERP\\backend\\core\\import_views.py", "source_location": "L1"}, {"id": "core_import_views_rationale_15", "label": "Validate import file without committing changes.", "file_type": "rationale", "source_file": "E:\\all downloads\\Pharmacy_ERP\\backend\\core\\import_views.py", "source_location": "L15"}, {"id": "core_import_views_rationale_60", "label": "Execute import transactionally. Rolls back on any failure.", "file_type": "rationale", "source_file": "E:\\all downloads\\Pharmacy_ERP\\backend\\core\\import_views.py", "source_location": "L60"}], "edges": [{"source": "e_all_downloads_pharmacy_erp_backend_core_import_views_py", "target": "mimetypes", "relation": "imports", "context": "import", "confidence": "EXTRACTED", "source_file": "E:\\all downloads\\Pharmacy_ERP\\backend\\core\\import_views.py", "source_location": "L2", "weight": 1.0}, {"source": "e_all_downloads_pharmacy_erp_backend_core_import_views_py", "target": "rest_framework", "relation": "imports_from", "context": "import", "confidence": "EXTRACTED", "source_file": "E:\\all downloads\\Pharmacy_ERP\\backend\\core\\import_views.py", "source_location": "L4", "weight": 1.0}, {"source": "e_all_downloads_pharmacy_erp_backend_core_import_views_py", "target": "rest_framework_decorators", "relation": "imports_from", "context": "import", "confidence": "EXTRACTED", "source_file": "E:\\all downloads\\Pharmacy_ERP\\backend\\core\\import_views.py", "source_location": "L5", "weight": 1.0}, {"source": "e_all_downloads_pharmacy_erp_backend_core_import_views_py", "target": "rest_framework_parsers", "relation": "imports_from", "context": "import", "confidence": "EXTRACTED", "source_file": "E:\\all downloads\\Pharmacy_ERP\\backend\\core\\import_views.py", "source_location": "L6", "weight": 1.0}, {"source": "e_all_downloads_pharmacy_erp_backend_core_import_views_py", "target": "rest_framework_response", "relation": "imports_from", "context": "import", "confidence": "EXTRACTED", "source_file": "E:\\all downloads\\Pharmacy_ERP\\backend\\core\\import_views.py", "source_location": "L7", "weight": 1.0}, {"source": "e_all_downloads_pharmacy_erp_backend_core_import_views_py", "target": "core_import_pipeline", "relation": "imports_from", "context": "import", "confidence": "EXTRACTED", "source_file": "E:\\all downloads\\Pharmacy_ERP\\backend\\core\\import_views.py", "source_location": "L9", "weight": 1.0}, {"source": "e_all_downloads_pharmacy_erp_backend_core_import_views_py", "target": "core_import_views_import_dry_run", "relation": "contains", "confidence": "EXTRACTED", "source_file": "E:\\all downloads\\Pharmacy_ERP\\backend\\core\\import_views.py", "source_location": "L14", "weight": 1.0}, {"source": "e_all_downloads_pharmacy_erp_backend_core_import_views_py", "target": "core_import_views_import_execute", "relation": "contains", "confidence": "EXTRACTED", "source_file": "E:\\all downloads\\Pharmacy_ERP\\backend\\core\\import_views.py", "source_location": "L59", "weight": 1.0}, {"source": "e_all_downloads_pharmacy_erp_backend_core_import_views_py", "target": "core_import_views_detect_format", "relation": "contains", "confidence": "EXTRACTED", "source_file": "E:\\all downloads\\Pharmacy_ERP\\backend\\core\\import_views.py", "source_location": "L93", "weight": 1.0}, {"source": "core_import_views_detect_format", "target": "str", "relation": "references", "context": "parameter_type", "confidence": "EXTRACTED", "source_file": "E:\\all downloads\\Pharmacy_ERP\\backend\\core\\import_views.py", "source_location": "L93", "weight": 1.0}, {"source": "core_import_views_detect_format", "target": "str", "relation": "references", "context": "return_type", "confidence": "EXTRACTED", "source_file": "E:\\all downloads\\Pharmacy_ERP\\backend\\core\\import_views.py", "source_location": "L93", "weight": 1.0}, {"source": "core_import_views_import_dry_run", "target": "core_import_views_detect_format", "relation": "calls", "context": "call", "confidence": "EXTRACTED", "source_file": "E:\\all downloads\\Pharmacy_ERP\\backend\\core\\import_views.py", "source_location": "L21", "weight": 1.0}, {"source": "core_import_views_import_execute", "target": "core_import_views_detect_format", "relation": "calls", "context": "call", "confidence": "EXTRACTED", "source_file": "E:\\all downloads\\Pharmacy_ERP\\backend\\core\\import_views.py", "source_location": "L66", "weight": 1.0}, {"source": "core_import_views_rationale_1", "target": "e_all_downloads_pharmacy_erp_backend_core_import_views_py", "relation": "rationale_for", "confidence": "EXTRACTED", "source_file": "E:\\all downloads\\Pharmacy_ERP\\backend\\core\\import_views.py", "source_location": "L1", "weight": 1.0}, {"source": "core_import_views_rationale_15", "target": "core_import_views_import_dry_run", "relation": "rationale_for", "confidence": "EXTRACTED", "source_file": "E:\\all downloads\\Pharmacy_ERP\\backend\\core\\import_views.py", "source_location": "L15", "weight": 1.0}, {"source": "core_import_views_rationale_60", "target": "core_import_views_import_execute", "relation": "rationale_for", "confidence": "EXTRACTED", "source_file": "E:\\all downloads\\Pharmacy_ERP\\backend\\core\\import_views.py", "source_location": "L60", "weight": 1.0}], "raw_calls": [{"caller_nid": "core_import_views_import_dry_run", "callee": "read", "is_member_call": true, "source_file": "E:\\all downloads\\Pharmacy_ERP\\backend\\core\\import_views.py", "source_location": "L20"}, {"caller_nid": "core_import_views_import_dry_run", "callee": "BulkImportEngine", "is_member_call": false, "source_file": "E:\\all downloads\\Pharmacy_ERP\\backend\\core\\import_views.py", "source_location": "L25"}, {"caller_nid": "core_import_views_import_dry_run", "callee": "dry_run", "is_member_call": true, "source_file": "E:\\all downloads\\Pharmacy_ERP\\backend\\core\\import_views.py", "source_location": "L26"}, {"caller_nid": "core_import_views_import_execute", "callee": "read", "is_member_call": true, "source_file": "E:\\all downloads\\Pharmacy_ERP\\backend\\core\\import_views.py", "source_location": "L65"}, {"caller_nid": "core_import_views_import_execute", "callee": "BulkImportEngine", "is_member_call": false, "source_file": "E:\\all downloads\\Pharmacy_ERP\\backend\\core\\import_views.py", "source_location": "L70"}, {"caller_nid": "core_import_views_import_execute", "callee": "execute", "is_member_call": true, "source_file": "E:\\all downloads\\Pharmacy_ERP\\backend\\core\\import_views.py", "source_location": "L71"}, {"caller_nid": "core_import_views_detect_format", "callee": "guess_type", "is_member_call": true, "source_file": "E:\\all downloads\\Pharmacy_ERP\\backend\\core\\import_views.py", "source_location": "L94"}, {"caller_nid": "core_import_views_detect_format", "callee": "endswith", "is_member_call": true, "source_file": "E:\\all downloads\\Pharmacy_ERP\\backend\\core\\import_views.py", "source_location": "L95"}, {"caller_nid": "core_import_views_detect_format", "callee": "lower", "is_member_call": true, "source_file": "E:\\all downloads\\Pharmacy_ERP\\backend\\core\\import_views.py", "source_location": "L95"}, {"caller_nid": "core_import_views_detect_format", "callee": "endswith", "is_member_call": true, "source_file": "E:\\all downloads\\Pharmacy_ERP\\backend\\core\\import_views.py", "source_location": "L97"}, {"caller_nid": "core_import_views_detect_format", "callee": "lower", "is_member_call": true, "source_file": "E:\\all downloads\\Pharmacy_ERP\\backend\\core\\import_views.py", "source_location": "L97"}, {"caller_nid": "core_import_views_detect_format", "callee": "ValueError", "is_member_call": false, "source_file": "E:\\all downloads\\Pharmacy_ERP\\backend\\core\\import_views.py", "source_location": "L99"}]}